Flask_Init-0.0.2.dist-info/DESCRIPTION.rst
Flask_Init-0.0.2.dist-info/METADATA
Flask_Init-0.0.2.dist-info/RECORD
Flask_Init-0.0.2.dist-info/WHEEL
Flask_Init-0.0.2.dist-info/entry_points.txt
Flask_Init-0.0.2.dist-info/metadata.json
Flask_Init-0.0.2.dist-info/top_level.txt
flask_init/__init__.py
flask_init/commands.py
flask_init/helper.py
