Metadata-Version: 2.0
Name: Flask-Init
Version: 0.0.2
Summary: Easy way to create Flask Web application
Home-page: https://github.com/rajasimon/flask-init
Author: Raja Simon
Author-email: rajasimon@icloud.com
License: See License
Platform: any
Classifier: Environment :: Web Environment
Classifier: Intended Audience :: Developers
Classifier: License :: OSI Approved :: MIT License
Classifier: Operating System :: OS Independent
Classifier: Programming Language :: Python
Classifier: Topic :: Internet :: WWW/HTTP :: Dynamic Content
Classifier: Topic :: Software Development :: Libraries :: Python Modules
Requires-Dist: Flask
